{"celery greens": [["vegetable herb", null]], "salmon trout": [["salmon similar", null]], "white mushroom": [["mushrooms", null]], "baking decorations": [["food", null]], "elderflower umbel": [["food", null]], "mozzarella stick": [["mozzarella", null]], "muffin baking mix": [["baking mix", null]], "smoked raclette cheese": [["flavored cheese varieties", null], ["semi hard cheese", null]], "sour gummy candy": [["sour candy", null]], "lambs lettuce": [["leafy vegetables", null]], "fondants icing": [["food", null]], "albeli": [["food", null]], "caramel liqueur": [["liqueur", null]], "cake decorating pen": [["food", null]], "sweet potato": [["tubers", null]], "lemongrass": [["herbs spices", "fresh peppermint"], ["herbs spices", "fresh rosemary"], ["herbs spices", "fresh lemon balm"], ["herbs spices", "fresh marjoram"], ["herbs spices", "fresh basil"], ["herbs spices", "fresh tarragon"], ["herbs spices", "fresh orange thyme"], ["herbs spices", "fresh thyme"], ["herbs spices", "fresh thai basil"]], "frozen spinach": [["mixed vegetables", null], ["leafy vegetables", null]], "cheese skewers": [["flavored cheese varieties", null]], "cream": [["food", "vanilla cream"], ["food", "cream cheese"], ["food", "clotted cream"], ["food", "ice cream sorbet"], ["food", "sour half cream"]], "okra": [["vegetables", null]], "sweet chili sauce": [["seasoning", "sweet soy sauce"]], "stone fruits": [["other fruits", null]], "fennel": [["vegetable herb", "fennel greens"], ["whole spices", "fennel seeds"]], "canned mushrooms marinated in oil": [["plant based oils", null], ["canned vegetables", null]], "cacao nibs": [["food", null]], "pea sprouts": [["sprouts seedlings", null], ["legumes", null]], "grischuna minipic": [["food", null]], "greek yogurt with honey": [["yogurts quarks", null]], "beer": [["beer apple wine", null]], "corn fed chicken breast": [["chicken breast", null]], "apple wine": [["alcoholic beverages", null]], "licorice root": [["root vegetables", null]], "mettwurst": [["food", null]], "whole grain pasta": [["pasta and noodles", null]], "vanilla flavor": [["flavors", null]], "veal cutlets from the nut": [], "almond cookies": [["cookies", null]], "goose meat": [["meat meat substitute products", null]], "beer radish": [["meat meat substitute products", null]], "fresh parsley": [["herbs spices", "fresh chives"], ["herbs spices", "fresh basil"], ["herbs spices", "fresh flat leaf parsley"], ["herbs spices", "fresh coriander"], ["herbs spices", "fresh orange thyme"], ["herbs spices", "fresh thai basil"], ["herbs spices", "fresh wild garlic"], ["herbs spices", "fresh peppermint"], ["herbs spices", "fresh savory"], ["herbs spices", "fresh italian herbs"], ["herbs spices", "fresh tarragon"], ["herbs spices", "fresh cut garlic"], ["herbs spices", "fresh lemon thyme"], ["herbs spices", "fresh sage"], ["herbs spices", "fresh chervil"], ["herbs spices", "fresh rosemary"], ["herbs spices", "fresh lemon balm"], ["herbs spices", "fresh oregano"], ["herbs spices", "fresh marjoram"], ["herbs spices", "fresh thyme"]], "thai jasmine rice": [["cereal", null]], "sugar": [["food", "sugar glaze"], ["food", "whole cane sugar"]], "dlicorn minced": [["meat meat substitute products", null]], "frozen pomme duchesse": [["prepared ingredients", null]], "red leaf lettuce": [["leaf lettuce", null]], "herb mustard": [["seasoning", null]], "veal liver": [["offal", "veal kidneys"]], "brook trout": [["salmon similar", null]], "amaretti": [["cookies", null]], "frozen berry mix": [["mixed vegetables", null], ["berries", "frozen blueberry"], ["berries", "frozen raspberry"], ["berries", "frozen cranberry"]], "cream quark": [["yogurts quarks", null]], "gin": [["spirits", null]], "apricot ice cream": [["ice cream sorbet", null]], "flatfish": [["food", null]], "chia seeds": [["seeds", null]], "veal sausage": [["veal", null]], "azuki bean paste": [["fruit compotes pastes", null], ["legumes", null]], "heart cherry": [["fruit vegetables", null], ["fruit juice", null], ["candied fruits", null]], "colored fondant": [["food", null]], "garlic clove": [["garlic", null]], "nut seed mixes": [["processed nuts seeds", null]], "dry vermouth": [["vermouth", null]], "strawberry jam": [["jams jellies", null]], "creole rice": [["cereal", null]], "chili raclette cheese": [["flavored cheese varieties", null]], "veal feet": [["veal", null]], "wild broth": [["broths", null]], "ham": [["cold cuts", "cooked ham"], ["cold cuts", "sliced ham bacon"], ["cold cuts", "smoked ham"], ["cold cuts", "smoked cooked ham"]], "beef sirloin steak": [["beef sirloin", null]], "coop jam sugar": [["jams jellies", null]], "poppy": [["seeds", "sunflower seed"], ["seeds", "peeled hemp seed"]], "pickled pepper": [["whole spices", null], ["pickles", "pickled peperoncino"], ["pickles", "pickled ginger"], ["pickles", "pickled green peppercorn"], ["pickles", "pickled salt lemon"], ["pickles", "pickled onion"]], "fleur de sel": [["seasoning", null]], "lumpfish roe": [["products from fish seafood", null]], "fruit liqueur": [["liqueur", null]], "kernel roll": [["bread roll", null]], "dried rosemary": [["dried herbs", null]], "black lentils from the can": [["canned vegetables", null]], "guetzli": [["food", null]], "t bone steak": [["beef", "beef sirloin"], ["beef", "beef rump"], ["beef", "beef cheeks"], ["beef", "beef stew"], ["beef", "limousin sirloin steak"], ["beef", "beef shank"], ["beef", "beef ribeye"], ["beef", "oxtail"], ["beef", "beef cutlet"], ["beef", "beef tomahawk steak"], ["beef", "beef fillet medallion"], ["beef", "roast beef"]], "flaxseed": [["processed nuts seeds", "ground almond"], ["processed nuts seeds", "ground hazelnut"]], "betty bossi shanghai asian wok mix": [["mixed vegetables", null], ["prepared ingredients", null]], "green tabasco": [["herbs spices", "green curry paste"]], "dark bread": [["bread", null]], "fondue cheese mix moiti moiti": [["flavored cheese varieties", null]], "floury boiled potatoes": [["prepared ingredients", null], ["tubers", null]], "plum yogurt": [["yogurts quarks", null]], "passion fruit juice": [["fruit juice", null]], "non alcoholic beer apple wine": [["non alcoholic beverages", null]], "clear apple juice": [["apple juice", null]], "bell minced meatballs": [["ground meat", null], ["meatballs", null]], "chickpea flour": [["flour", null]], "frozen green pea": [["legumes", null]], "early potato": [["tubers", null]], "romanesco": [["cruciferous", null]], "ovomaltine noir chocolate": [["chocolates", null]], "other oily saltwater fish": [["fish seafood", null]], "grissini": [["flatbreads", null]], "tapenade": [["seasoning", "ajvar"]], "piadina": [["flatbreads", "whole grain tortilla wrap"]], "pearl sugar": [["food", null]], "iceberg lettuce": [["leafy vegetables", null]], "cailler cuisine cocoa powder": [["cocoa powder", null]], "psyllium husks": [["seeds", null], ["dried vegetables", null]], "dry sparkling wine": [["alcoholic beverages", null]], "nutmeg pumpkin": [["herbs spices", null]], "guinea fowl meat": [["meat meat substitute products", "guinea fowl breast"], ["meat meat substitute products", "guinea fowl"]], "red grape": [["berries", null]], "sesame oil": [["plant based oils", null]], "calvados": [["spirits", "cachaa"]], "hazelnut spread": [["bread spreads", null]], "spelt cake dough": [["cake dough", null]], "almond mush": [["processed nuts seeds", null]], "cornbread": [["bread", null], ["sweet baked goods", null]], "salted cashew nut": [["nuts", null], ["spiced nuts", "salted peanut"], ["spiced nuts", "salted almond"]], "tuna": [["fish seafood", "giant shrimp"], ["fish seafood", "frozen shrimp"], ["fish seafood", "cooked giant shrimp"], ["fish seafood", "cooked shrimp"]], "white toblerone": [["chocolates", null]], "gingerbread dough": [["prepared ingredients", null]], "fermented seasonings": [["herbs spices", null]], "hawaii salt": [["salts", null]], "cotton candy": [["soft candies", null]], "beef burger": [["beef", "beef sirloin"], ["beef", "beef rump"], ["beef", "beef stew"], ["beef", "beef shank"], ["beef", "beef cutlet"], ["beef", "beef tomahawk steak"], ["beef", "beef fillet medallion"]], "tapioca starch": [["starch", null]], "frozen broccoli": [["mixed vegetables", null], ["cruciferous", null]], "candied peel": [["citrus fruit peels", null], ["candied fruits", "candied citrus peel"]], "vanilla sugar": [["sugar alternatives", null]], "wine": [["alcoholic beverages", "sherry"], ["alcoholic beverages", "dry sherry"], ["alcoholic beverages", "dry white wine"], ["alcoholic beverages", "champagne"], ["alcoholic beverages", "champagne demi sec"]], "plum brandy": [["liqueur", null], ["spirits", null]], "medium hot mustard": [["seasoning", null]], "gluten free risoni made from lentils and chickpeas": [["pasta and noodles", null], ["other processed foods", "gluten free gnocchi"]], "grape leaf in salt water": [["seafood canned", null]], "puffed amaranth": [["breakfast flakes", "puffed rice"]], "dried white beans": [["legumes", "dried borlotti beans"]], "cod": [["cod similar", "cod fillet"], ["cod similar", "deep frozen hake"], ["cod similar", "frozen pollock"], ["cod similar", "hake"], ["cod similar", "frozen cod"], ["cod similar", "pollock"]], "strawberry jelly": [["jams jellies", "strawberry rhubarb jam"]], "ice cream cone": [["ice cream sorbet", null]], "emmi gala cheese": [["flavored cheese varieties", null], ["semi hard cheese", null]], "maizena": [["food", null]], "peach syrup": [["syrup", null]], "nettle leaves": [["herbs spices", null], ["leafy vegetables", null]], "cola drink": [["soft drinks", null]], "alfalfa arugula sprouts": [["sprouts seedlings", null]], "seedless grape": [["grape", null]], "sour cherry": [["fruit", null], ["cherry", null]], "34 fat quark": [["yogurts quarks", "whole milk quark"]], "sweet and sour sauce": [["seasoning", "sweet soy sauce"], ["seasoning", "sweet mustard"]], "blood orange juice": [["fruit juice", null], ["citrus fruits", null]], "apple cider vinegar": [["vinegar", null]], "juniper berry": [["berries", null]], "mixed bell peppers": [["mixed vegetables", null]], "soft cheese": [["food", null]], "lamb loin": [["lamb meat", "lamb stew"], ["lamb meat", "lamb shoulder"], ["lamb meat", "lamb rump"]], "milk chocolate": [["chocolates", null]], "rye wholemeal flour": [["wholemeal flour", null], ["rye flour", null]], "crunchy roll dough": [["bread roll", null], ["prepared ingredients", null]], "emmental": [["food", null]], "candied sugar": [["candied fruits", null]], "nail powder": [], "marinated feta with garlic": [["flavored cheese varieties", null]], "wasabi paste": [["herbs spices", null]], "cornelian cherry": [["candied fruits", null]], "other snacks": [["food", null]], "plant based meat alternatives": [["meat meat substitute products", "sunflower mince nature"], ["meat meat substitute products", "planted chicken nature"]], "galangal": [["food", null]], "tomato puree": [["fruit compotes pastes", null]], "sherry vinegar": [["vinegar", null]], "fresh dill": [["herbs spices", null]], "summer truffle": [["mushrooms", null]], "sweet potato chips": [["chips", null]], "strawberry ice cream": [["ice cream sorbet", null]], "mustard": [["seasoning", "hot mustard"], ["seasoning", "coarse grained mustard"]], "papaya": [["food", null]], "apple jelly": [["jams jellies", null]], "vintners bread": [["bread", null]], "grilled cheese": [["flavored cheese varieties", null]], "sea bass": [["fish seafood", null]], "gluten free butter cookies": [], "truffle oil": [["plant based oils", null]], "boiled potatoes": [["prepared ingredients", null]], "peach": [["food", null]], "tofu with provence herbs": [["herbs spices", null], ["meat meat substitute products", null]], "sweetened condensed milk": [["condensed milk", null]], "gelatin": [["thickening agent", null]], "salt": [["salts", "salt pepper"]], "curd": [["yogurts quarks", "plain quark"], ["yogurts quarks", "low fat curd cheese"], ["yogurts quarks", "14 fat quark"], ["yogurts quarks", "whole milk quark"]], "peach jam": [["jams jellies", null]], "coconut cream": [["cream cheese", null]], "potato flakes": [["cereal", null], ["dried vegetables", null]], "vegetable mix": [["mixed vegetables", null]], "falafel": [["other processed foods", null]], "ice cubes": [["non alcoholic beverages", null]], "blackberry sorbet": [["ice cream sorbet", null]], "lychee": [["food", null]], "soft drink concentrates": [["fruit concentrates", null]], "tropical fruits": [["other fruits", null]], "zwieback": [["food", null]], "nuts seeds": [["food", null]], "coffee chocolate": [["chocolates", null], ["tea coffee", null]]}